setup.py
DamageFilter.egg-info/PKG-INFO
DamageFilter.egg-info/SOURCES.txt
DamageFilter.egg-info/dependency_links.txt
DamageFilter.egg-info/entry_points.txt
DamageFilter.egg-info/requires.txt
DamageFilter.egg-info/top_level.txt
src/DamageFilter.py
src/__init__.py
src/creat_metrics.py
src/defaults.py
src/filter_bias.py
src/main.py
src/utils.py
src/version.py