Metadata-Version: 1.0
Name: DamageFilter
Version: 1.2.0
Summary: For Artifact DNA damage filter
Home-page: UNKNOWN
Author: Yong Deng
Author-email: ['dengyong@geneplus.org.cn', 'yodeng@tju.edu.cn']
License: MIT
Platform: UNKNOWN
